Metadata-Version: 2.1
Name: EgC-Demo-Package-test
Version: 0.0.3
Summary: A small example package from EGC
Home-page: https://github.com/EgC-Team/EngineeringGoesCloud
Author: EgC-Team
Author-email: mail@engineering-goes-cloud.de
License: UNKNOWN
Platform: UNKNOWN
Classifier: Programming Language :: Python :: 3
Classifier: License :: OSI Approved :: MIT License
Classifier: Operating System :: OS Independent
Requires-Python: >=3.7
Requires-Dist: numpy
Requires-Dist: xlrd
Provides-Extra: all
Requires-Dist: asammdf ; extra == 'all'
Requires-Dist: pytest ; extra == 'all'
Provides-Extra: analysisdrvcyc
Requires-Dist: asammdf ; extra == 'analysisdrvcyc'
Provides-Extra: modelingann
Requires-Dist: pytest ; extra == 'modelingann'
